{
  "title": "机器",
  "createMachine": "添加机器",
  "machineName": "机器名称",
  "team": "团队",
  "region": "地区",
  "bridge": "桥",
  "queueItems": "队列项目",
  "vaultVersion": "保险库版",
  "vault": "金库",
  "filterByRegion": "按区域过滤",
  "filterByBridge": "桥过滤",
  "filterByTeam": "团队过滤",
  "groupBy": "组",
  "groupByBridge": "桥",
  "groupByTeam": "团队",
  "groupByRegion": "地区",
  "groupByRepository": "存储库",
  "groupByMounted": "安装",
  "groupByUnmounted": "卸载",
  "groupByStatus": "地位",
  "groupByGrand": "大存储库",
  "clearFilters": "清除过滤器",
  "searchMachineName": "搜索计算机名称",
  "searchPlaceholder": "搜索机...",
  "viewMode": "查看模式",
  "viewBy": "查看",
  "tableView": "机器",
  "gridView": "存储库",
  "machineCount": "机器| 机器",
  "itemCount": "项目| 项目",
  "queue": "队列",
  "editMachine": "编辑机器",
  "delete": "删除",
  "confirmDelete": "删除机器",
  "deleteWarning": "您确定要删除机器“ {{name}}”？ 该动作不能撤消。",
  "deleteSuccess": "机器成功删除了",
  "deleteError": "无法删除机器",
  "createSuccess": "机器成功创建了",
  "updateSuccess": "机器成功更新了",
  "vaultUpdateSuccess": "机器保险库配置成功更新了",
  "autoSetupAfterCreation": "机器创建后自动运行设置",
  "setupQueued": "机器成功创建了。 设置已排队。",
  "setupQueuedForSubmission": "机器成功创建了。 设置排队以提交。",
  "machineCreatedButSetupFailed": "成功创建的机器，但是设置无法排队。",
  "form": {
    "title": {
      "create": "创建新机器",
      "edit": "编辑机器",
      "vault": "配置机器库"
    },
    "selectTeam": "选择团队",
    "selectBridge": "选择桥",
    "machineNamePlaceholder": "输入机器名称",
    "vaultConfig": "保险库配置（JSON）"
  },
  "readOnlyNote": "仅查看",
  "readOnlyDescription": "这是只读的视图。 要编辑机器或执行操作，请访问",
  "goToMachinesPage": "机器页面",
  "systemFunctions": "机器功能",
  "addSystemFunction": "将系统功能添加到队列",
  "availableFunctions": "可用功能",
  "searchFunctions": "搜索功能...",
  "configure": "配置",
  "machine": "机器",
  "placeholders": {
    "selectMachine": "选择一台机器"
  },
  "trace": "痕迹",
  "selectMachine": "选择机器",
  "noMachinesFound": "找不到机器",
  "priority": "优先事项",
  "priorityLow": "低的",
  "priorityNormal": "普通的",
  "priorityHigh": "高的",
  "description": "描述（可选）",
  "descriptionPlaceholder": "为此队列项目添加自定义描述",
  "selectFunctionToConfigure": "选择要配置的功能",
  "addToQueue": "添加到队列",
  "defaultsApplied": "自动应用默认值",
  "queueItemCreated": "创建队列项目",
  "queueItemCreatedMessage": "队列项目已成功创建。",
  "connectivityTest": "连接测试",
  "runTest": "运行测试",
  "testing": "测试...",
  "testingMachine": "测试{{MachineName}} ...",
  "connectivityTestDescription": "该测试将依次向每台机器发送“ Ping”功能，以验证连接性。",
  "connectionSuccessful": "连接成功",
  "connectionFailed": "连接失败",
  "testTimeout": "测试超时 - 未收到回应",
  "allMachinesConnected": "所有{{count}}机器已成功连接",
  "machinesConnectedWithFailures": "{{{SuccessCount}}机器连接，{{failedCount}}失败",
  "totalMachines": "总机器",
  "connected": "连接",
  "failed": "失败的",
  "averageResponse": "平均响应",
  "responseTime": "响应时间",
  "status": "地位",
  "pending": "待办的",
  "message": "信息",
  "runFunction": "运行功能",
  "connectionTestQueued": "连接测试排队成功",
  "connectionTestFailed": "无法排队连接测试",
  "testingConnection": "测试连接...",
  "remote": "偏僻的",
  "remoteOperations": "远程操作",
  "createRepo": "创建回购",
  "pullRepo": "拉回购",
  "runAction": "在服务器上运行",
  "advanced": "先进的",
  "lastUpdated": "最后更新",
  "statusUnknown": "未知",
  "currentMachine": "当前机器",
  "justNow": "现在",
  "minutesAgo": "{{count}}分钟前",
  "minutesAgo_plural": "{{count}}几分钟前",
  "hoursAgo": "{{count}}一个小时前",
  "hoursAgo_plural": "{{count}}小时前",
  "daysAgo": "{{count}}一天前",
  "daysAgo_plural": "{{count}}几天前",
  "distributedStorageCluster": "分布式存储",
  "assignToCluster": "分配到群集",
  "changeClusterAssignment": "更改集群分配",
  "selectCluster": "选择一个群集或空无一人",
  "clusterAssignmentHelp": "空白以从其当前集群中统一机器",
  "currentClusterAssignment": "当前分配给群集：{{cluster}}",
  "clusterAssignedSuccess": "分配给集群{{cluster}}的机器成功",
  "clusterUnassignedSuccess": "从集群中未分配的机器成功地",
  "clusterRemovedSuccess": "成功从集群中删除的机器",
  "assignmentStatus": {
    "available": "可用的",
    "cluster": "分配给群集",
    "image": "分配给图像",
    "clone": "分配给克隆",
    "title": "分配状态"
  },
  "bulkOperations": {
    "assignToClone": "分配给克隆",
    "removeFromClone": "从克隆中取出",
    "validating": "验证机器可用性...",
    "assignmentSuccess": "成功分配{{count}}机器",
    "assignmentPartial": "分配的{{{Success}} {{attry}}机器",
    "removalSuccess": "成功删除{{count}}机器",
    "selectMachines": "选择要分配的机器",
    "selectedCount": "{{count}}计算机",
    "selectedCount_plural": "{{count}}选择了机器"
  },
  "bulkActions": {
    "selected": "{{count}}选择了机器",
    "assignToCluster": "分配到群集",
    "removeFromCluster": "从集群中删除",
    "viewAssignmentStatus": "查看分配状态"
  },
  "validation": {
    "sshPasswordNotAllowed": "没有配置SSH密钥，就无法使用SSH密码。 请先设置SSH键或删除密码。",
    "alreadyAssigned": "机器已经分配给{{resourceType}}：{{resourcename}}",
    "noMachinesSelected": "请选择至少一台机器",
    "allMachinesUnavailable": "所有选定的机器都不可用",
    "machineNotAvailable": "机器{{MachineName}}无法分配"
  },
  "bulkAssignDescription": "所有选定的机器将分配给同一集群",
  "noMachinesWithClusters": "所选的机器均未分配给群集",
  "removeFromClusterWarning": "您确定要从其簇中删除{{count}}机器吗？",
  "removeFromClusterDescription": "这将使机器从其当前簇统一",
  "noAvailableMachinesForClone": "没有用于克隆分配的机器",
  "selectMachines": "选择机器",
  "noAvailableMachines": "没有可用的机器",
  "machines": "机器",
  "currentMachineAssignment": "当前分配给：{{Machine}}",
  "manage": "管理"
}